iso_env/__init__.py
iso_env/api.py
iso_env/cli.py
iso_env/run.py
iso_env/types.py
iso_env/util.py
iso_env/assets/example.txt
uv_iso_env-1.0.43.dist-info/licenses/LICENSE
uv_iso_env-1.0.43.dist-info/METADATA
uv_iso_env-1.0.43.dist-info/WHEEL
uv_iso_env-1.0.43.dist-info/entry_points.txt
uv_iso_env-1.0.43.dist-info/top_level.txt
uv_iso_env-1.0.43.dist-info/RECORD
