Metadata-Version: 2.4
Name: uv_iso_env
Version: 1.0.43
Summary: isolated environment2, re-written using uv
Home-page: https://github.com/zackees/iso-env
Maintainer: Zachary Vorhies
License: BSD 3-Clause License
Keywords: template-python-cmd
Classifier: Programming Language :: Python :: 3
Requires-Python: >=3.10
License-File: LICENSE
Requires-Dist: twine>=6.0.1
Requires-Dist: uv>=0.6.4
Dynamic: home-page
Dynamic: license-file
Dynamic: maintainer
